torchsaber/__init__.py
torchsaber/torchsaber.py
torchsaber-1.0.2.dist-info/METADATA
torchsaber-1.0.2.dist-info/WHEEL
torchsaber-1.0.2.dist-info/top_level.txt
torchsaber-1.0.2.dist-info/RECORD
