Metadata-Version: 2.1
Name: torchsaber
Version: 1.0.2
Summary: Elegant dimensions for a more civilized age
Home-page: https://github.com/kach/torchsaber
Author: Kartik Chandra
Author-email: 
License: UNKNOWN
Platform: UNKNOWN
Classifier: Programming Language :: Python :: 3
Classifier: Operating System :: OS Independent
Requires-Python: >=3.6
